{
    "version": "https://jsonfeed.org/version/1",
    "title": "SALT90",
    "description": "",
    "home_page_url": "https://salt90.github.io",
    "feed_url": "https://salt90.github.io/feed.json",
    "user_comment": "",
    "author": {
        "name": "SALT ARTS"
    },
    "items": [
        {
            "id": "https://salt90.github.io/the-lady-with-flowers/",
            "url": "https://salt90.github.io/the-lady-with-flowers/",
            "title": "The Lady with Flowers",
            "summary": "Medium: Digital Availability: On Redbubble",
            "content_html": "<div class=\"gallery\"   >\n<figure class=\"gallery__item\"><a href=\"https://salt90.github.io/media/posts/2/gallery/work-image-2.jpg\" ><img src=\"https://salt90.github.io/media/posts/2/gallery/work-image-2-thumbnail.jpg\" alt=\"\" width=\"768\" height=\"768\"></a></figure>\n<figure class=\"gallery__item\"><a href=\"https://salt90.github.io/media/posts/2/gallery/work-image-1.jpg\" ><img src=\"https://salt90.github.io/media/posts/2/gallery/work-image-1-thumbnail.jpg\" alt=\"\" width=\"768\" height=\"768\"></a></figure>\n<figure class=\"gallery__item\"><a href=\"https://salt90.github.io/media/posts/2/gallery/work-image.jpg\" ><img src=\"https://salt90.github.io/media/posts/2/gallery/work-image-thumbnail.jpg\" alt=\"\" width=\"768\" height=\"769\"></a></figure>\n</div>\n<p>Medium: Digital<br>Availability: <a href=\"https://www.redbubble.com/people/ontrip/works/40661423-the-lady-with-flowers\" title=\"Buy prints and products\" target=\"_blank\" rel=\"noopener noreferrer\">On Redbubble</a></p>",
            "image": "https://salt90.github.io/media/posts/2/work-image-1.jpg",
            "author": {
                "name": "SALT ARTS"
            },
            "tags": [
            ],
            "date_published": "2019-08-19T01:45:48+02:00",
            "date_modified": "2019-08-19T01:45:48+02:00"
        },
        {
            "id": "https://salt90.github.io/hello-world/",
            "url": "https://salt90.github.io/hello-world/",
            "title": "Hello World",
            "summary": "Hello",
            "content_html": "Hello",
            "author": {
                "name": "SALT ARTS"
            },
            "tags": [
            ],
            "date_published": "2019-08-19T01:30:04+02:00",
            "date_modified": "2019-08-19T01:30:04+02:00"
        }
    ]
}
